ICO3Core/__init__.py
ICO3Core/Module/ICO3LocalModule.py
ICO3Core/Module/ICO3ModulePlugin.py
ICO3Core/Module/__init__.py
ICO3Core/Node/ICO3LocalNode.py
ICO3Core/Node/__init__.py
ICO3Plugin/__init__.py
ICO3Plugin/ConnectionManager/ICO3ConnectionLink.py
ICO3Plugin/ConnectionManager/ICO3ConnectionManager.py
ICO3Plugin/ConnectionManager/ICO3IPInitiatorConnectionManager.py
ICO3Plugin/ConnectionManager/ICO3IPLink.py
ICO3Plugin/ConnectionManager/ICO3IPListenerConnectionManager.py
ICO3Plugin/ConnectionManager/ICO3IdentificationProcess.py
ICO3Plugin/ConnectionManager/ICO3PhyDataBuffer.py
ICO3Plugin/ConnectionManager/__init__.py
ICO3Plugin/Message/ICO3Message.py
ICO3Plugin/Message/ICO3MessageHeader.py
ICO3Plugin/Message/ICO3UUID.py
ICO3Plugin/Message/__init__.py
ICO3Plugin/Plugin/ICO3AppParameter.py
ICO3Plugin/Plugin/ICO3FramePlugin.py
ICO3Plugin/Plugin/ICO3NodeWayProcessor.py
ICO3Plugin/Plugin/__init__.py
ICO3Plugin/Plugin/ico3plugin.py
ICO3Plugin/Plugin/ico3plugincreator.py
ICO3PluginCollection/__init__.py
ICO3PluginCollection/MessageView/MessageFramePlugin.py
ICO3PluginCollection/MessageView/MinFramePlugin.py
ICO3PluginCollection/MessageView/__init__.py
ICO3Server/ICO3BasicStarter.py
ICO3Server/ICO3Server.py
ICO3Server/ICO3StartIcocube.py
ICO3Server/__init__.py
ICO3Utilities/ICO3TokenizerParam.py
ICO3Utilities/InstallWheelFile.py
ICO3Utilities/__init__.py
ICO3Utilities/Debug/LogDebug.py
ICO3Utilities/Debug/__init__.py
ICO3Utilities/Xml/XmlProcess.py
ICO3Utilities/Xml/__init__.py
IcoCube-0.0.1a6.data/data/bitmaps/icocube.gif
IcoCube-0.0.1a6.dist-info/LICENSE.txt
IcoCube-0.0.1a6.dist-info/METADATA
IcoCube-0.0.1a6.dist-info/WHEEL
IcoCube-0.0.1a6.dist-info/top_level.txt
IcoCube-0.0.1a6.dist-info/RECORD
