Metadata-Version: 2.1
Name: IcoCube
Version: 0.0.1a6
Summary: ICOCUBE Python Core
Home-page: UNKNOWN
Author: Gilles PREVOT
Author-email: gilles.icocube@gmail.com
License: MIT
Platform: UNKNOWN
